{"flowContents":{"identifier":"8f23d57e-775a-3044-a314-9d0f58900aa2","instanceIdentifier":"8c743f56-1d79-1028-1516-759977e1d530","name":"ServersScopeControl","comments":"","position":{"x":712.0,"y":408.0},"processGroups":[],"remoteProcessGroups":[],"processors":[{"identifier":"5ab48c0b-351c-3a12-9ff2-ca0b7df74f60","instanceIdentifier":"8c743f6e-1d79-1028-db19-6e50f5a0a46c","name":"MainEvent","comments":"","position":{"x":-680.0,"y":-72.0},"type":"org.apache.nifi.processors.standard.GenerateFlowFile","bundle":{"group":"org.apache.nifi","artifact":"nifi-standard-nar","version":"1.20.0"},"properties":{"character-set":"UTF-8","File Size":"0B","mime-type":null,"generate-ff-custom-text":"[\n{\n    \"ResourceId\" : \"aaaaaaaaaaaaaaa\",\n    \"Status\" : \"Running\",\n    \"Applications\" : {\n        \"Antivirus\" : \"YES\",\n        \"DLP\" : \"YES\",\n        \"Firewall\" : \"YES\",\n        \"DiscEncryption\" : \"YES\"\n    }\n},\n{\n    \"ResourceId\" : \"bbbbbbbbbbbbbbb\",\n    \"Status\" : \"Stopped\",\n    \"Applications\" : {\n        \"Antivirus\" : \"NO\",\n        \"DLP\" : \"NO\",\n        \"Firewall\" : \"NO\",\n        \"DiscEncryption\" : \"NO\"\n    }\n},\n{\n    \"ResourceId\" : \"ccccccccccccccc\",\n    \"Status\" : \"Stopped\",\n    \"Applications\" : {\n        \"Antivirus\" : \"NO\",\n        \"DLP\" : \"NO\",\n        \"Firewall\" : \"NO\",\n        \"DiscEncryption\" : \"YES\"\n    }\n},\n{\n    \"ResourceId\" : \"ddddddddddddddd\",\n    \"Status\" : \"Running\",\n    \"Applications\" : {\n        \"Antivirus\" : \"NO\",\n        \"DLP\" : \"YES\",\n        \"Firewall\" : \"NO\",\n        \"DiscEncryption\" : \"YES\"\n    }\n}\n]","Batch Size":"1","Unique FlowFiles":"false","Data Format":"Text"},"propertyDescriptors":{"character-set":{"name":"character-set","displayName":"Character Set","identifiesControllerService":false,"sensitive":false},"File Size":{"name":"File Size","displayName":"File Size","identifiesControllerService":false,"sensitive":false},"mime-type":{"name":"mime-type","displayName":"Mime Type","identifiesControllerService":false,"sensitive":false},"generate-ff-custom-text":{"name":"generate-ff-custom-text","displayName":"Custom Text","identifiesControllerService":false,"sensitive":false},"Batch Size":{"name":"Batch Size","displayName":"Batch Size","identifiesControllerService":false,"sensitive":false},"Unique FlowFiles":{"name":"Unique FlowFiles","displayName":"Unique FlowFiles","identifiesControllerService":false,"sensitive":false},"Data Format":{"name":"Data Format","displayName":"Data Format","identifiesControllerService":false,"sensitive":false}},"style":{},"schedulingPeriod":"1 min","schedulingStrategy":"TIMER_DRIVEN","executionNode":"ALL","penaltyDuration":"30 sec","yieldDuration":"1 sec","bulletinLevel":"WARN","runDurationMillis":0,"concurrentlySchedulableTaskCount":1,"autoTerminatedRelationships":[],"scheduledState":"ENABLED","retryCount":10,"retriedRelationships":[],"backoffMechanism":"PENALIZE_FLOWFILE","maxBackoffPeriod":"10 mins","componentType":"PROCESSOR","groupIdentifier":"8f23d57e-775a-3044-a314-9d0f58900aa2"},{"identifier":"bd5f4a21-c580-3dfc-b35a-3aa084501223","instanceIdentifier":"8c743f87-1d79-1028-27ed-cb6be5dc3f5e","name":"serverReportingOK","comments":"","position":{"x":-368.0,"y":1976.0},"type":"org.apache.nifi.processors.kafka.pubsub.PublishKafka_2_6","bundle":{"group":"org.apache.nifi","artifact":"nifi-kafka-2-6-nar","version":"1.20.0"},"properties":{"compression.type":"none","attribute-name-regex":null,"bootstrap.servers":"#{IP}:9092","sasl.kerberos.principal":null,"sasl.kerberos.service.name":null,"kerberos-credentials-service":null,"kafka-key":null,"partition":null,"sasl.mechanism":"GSSAPI","max.block.ms":"5 sec","message-header-encoding":"UTF-8","kerberos-user-service":null,"message-demarcator":null,"transactional-id-prefix":null,"ack.wait.time":"5 secs","sasl.username":null,"use-transactions":"true","acks":"all","aws.profile.name":null,"security.protocol":"PLAINTEXT","ssl.context.service":null,"max.request.size":"1 MB","sasl.token.auth":"false","Failure Strategy":"Route to Failure","partitioner.class":"org.apache.kafka.clients.producer.internals.DefaultPartitioner","sasl.kerberos.keytab":null,"topic":"serverReportingOK","key-attribute-encoding":"utf-8"},"propertyDescriptors":{"compression.type":{"name":"compression.type","displayName":"Compression Type","identifiesControllerService":false,"sensitive":false},"attribute-name-regex":{"name":"attribute-name-regex","displayName":"Attributes to Send as Headers (Regex)","identifiesControllerService":false,"sensitive":false},"bootstrap.servers":{"name":"bootstrap.servers","displayName":"Kafka Brokers","identifiesControllerService":false,"sensitive":false},"sasl.kerberos.principal":{"name":"sasl.kerberos.principal","displayName":"Kerberos Principal","identifiesControllerService":false,"sensitive":false},"sasl.kerberos.service.name":{"name":"sasl.kerberos.service.name","displayName":"Kerberos Service Name","identifiesControllerService":false,"sensitive":false},"kerberos-credentials-service":{"name":"kerberos-credentials-service","displayName":"Kerberos Credentials Service","identifiesControllerService":true,"sensitive":false},"kafka-key":{"name":"kafka-key","displayName":"Kafka Key","identifiesControllerService":false,"sensitive":false},"partition":{"name":"partition","displayName":"Partition","identifiesControllerService":false,"sensitive":false},"sasl.mechanism":{"name":"sasl.mechanism","displayName":"SASL Mechanism","identifiesControllerService":false,"sensitive":false},"max.block.ms":{"name":"max.block.ms","displayName":"Max Metadata Wait Time","identifiesControllerService":false,"sensitive":false},"message-header-encoding":{"name":"message-header-encoding","displayName":"Message Header Encoding","identifiesControllerService":false,"sensitive":false},"kerberos-user-service":{"name":"kerberos-user-service","displayName":"Kerberos User Service","identifiesControllerService":true,"sensitive":false},"message-demarcator":{"name":"message-demarcator","displayName":"Message Demarcator","identifiesControllerService":false,"sensitive":false},"transactional-id-prefix":{"name":"transactional-id-prefix","displayName":"Transactional Id Prefix","identifiesControllerService":false,"sensitive":false},"ack.wait.time":{"name":"ack.wait.time","displayName":"Acknowledgment Wait Time","identifiesControllerService":false,"sensitive":false},"sasl.username":{"name":"sasl.username","displayName":"Username","identifiesControllerService":false,"sensitive":false},"use-transactions":{"name":"use-transactions","displayName":"Use Transactions","identifiesControllerService":false,"sensitive":false},"acks":{"name":"acks","displayName":"Delivery Guarantee","identifiesControllerService":false,"sensitive":false},"aws.profile.name":{"name":"aws.profile.name","displayName":"AWS Profile Name","identifiesControllerService":false,"sensitive":false},"security.protocol":{"name":"security.protocol","displayName":"Security Protocol","identifiesControllerService":false,"sensitive":false},"ssl.context.service":{"name":"ssl.context.service","displayName":"SSL Context Service","identifiesControllerService":true,"sensitive":false},"max.request.size":{"name":"max.request.size","displayName":"Max Request Size","identifiesControllerService":false,"sensitive":false},"sasl.token.auth":{"name":"sasl.token.auth","displayName":"Token Authentication","identifiesControllerService":false,"sensitive":false},"Failure Strategy":{"name":"Failure Strategy","displayName":"Failure Strategy","identifiesControllerService":false,"sensitive":false},"partitioner.class":{"name":"partitioner.class","displayName":"Partitioner class","identifiesControllerService":false,"sensitive":false},"sasl.kerberos.keytab":{"name":"sasl.kerberos.keytab","displayName":"Kerberos Keytab","identifiesControllerService":false,"sensitive":false,"resourceDefinition":{"cardinality":"SINGLE","resourceTypes":["FILE"]}},"topic":{"name":"topic","displayName":"Topic Name","identifiesControllerService":false,"sensitive":false},"sasl.password":{"name":"sasl.password","displayName":"Password","identifiesControllerService":false,"sensitive":true},"key-attribute-encoding":{"name":"key-attribute-encoding","displayName":"Key Attribute Encoding","identifiesControllerService":false,"sensitive":false}},"style":{},"schedulingPeriod":"0 sec","schedulingStrategy":"TIMER_DRIVEN","executionNode":"ALL","penaltyDuration":"30 sec","yieldDuration":"1 sec","bulletinLevel":"WARN","runDurationMillis":0,"concurrentlySchedulableTaskCount":1,"autoTerminatedRelationships":[],"scheduledState":"ENABLED","retryCount":10,"retriedRelationships":[],"backoffMechanism":"PENALIZE_FLOWFILE","maxBackoffPeriod":"10 mins","componentType":"PROCESSOR","groupIdentifier":"8f23d57e-775a-3044-a314-9d0f58900aa2"},{"identifier":"735d6488-10b1-396f-aed4-2d4c6166c222","instanceIdentifier":"8c743f88-1d79-1028-0410-0f912f78ebca","name":"serverReportingNotOK","comments":"","position":{"x":-920.0,"y":1976.0},"type":"org.apache.nifi.processors.kafka.pubsub.PublishKafka_2_6","bundle":{"group":"org.apache.nifi","artifact":"nifi-kafka-2-6-nar","version":"1.20.0"},"properties":{"compression.type":"none","attribute-name-regex":null,"bootstrap.servers":"#{IP}:9092","sasl.kerberos.principal":null,"sasl.kerberos.service.name":null,"kerberos-credentials-service":null,"kafka-key":null,"partition":null,"sasl.mechanism":"GSSAPI","max.block.ms":"5 sec","message-header-encoding":"UTF-8","kerberos-user-service":null,"message-demarcator":null,"transactional-id-prefix":null,"ack.wait.time":"5 secs","sasl.username":null,"use-transactions":"true","acks":"all","aws.profile.name":null,"security.protocol":"PLAINTEXT","ssl.context.service":null,"max.request.size":"1 MB","sasl.token.auth":"false","Failure Strategy":"Route to Failure","partitioner.class":"org.apache.kafka.clients.producer.internals.DefaultPartitioner","sasl.kerberos.keytab":null,"topic":"serverReportingNotOK","key-attribute-encoding":"utf-8"},"propertyDescriptors":{"compression.type":{"name":"compression.type","displayName":"Compression Type","identifiesControllerService":false,"sensitive":false},"attribute-name-regex":{"name":"attribute-name-regex","displayName":"Attributes to Send as Headers (Regex)","identifiesControllerService":false,"sensitive":false},"bootstrap.servers":{"name":"bootstrap.servers","displayName":"Kafka Brokers","identifiesControllerService":false,"sensitive":false},"sasl.kerberos.principal":{"name":"sasl.kerberos.principal","displayName":"Kerberos Principal","identifiesControllerService":false,"sensitive":false},"sasl.kerberos.service.name":{"name":"sasl.kerberos.service.name","displayName":"Kerberos Service Name","identifiesControllerService":false,"sensitive":false},"kerberos-credentials-service":{"name":"kerberos-credentials-service","displayName":"Kerberos Credentials Service","identifiesControllerService":true,"sensitive":false},"kafka-key":{"name":"kafka-key","displayName":"Kafka Key","identifiesControllerService":false,"sensitive":false},"partition":{"name":"partition","displayName":"Partition","identifiesControllerService":false,"sensitive":false},"sasl.mechanism":{"name":"sasl.mechanism","displayName":"SASL Mechanism","identifiesControllerService":false,"sensitive":false},"max.block.ms":{"name":"max.block.ms","displayName":"Max Metadata Wait Time","identifiesControllerService":false,"sensitive":false},"message-header-encoding":{"name":"message-header-encoding","displayName":"Message Header Encoding","identifiesControllerService":false,"sensitive":false},"kerberos-user-service":{"name":"kerberos-user-service","displayName":"Kerberos User Service","identifiesControllerService":true,"sensitive":false},"message-demarcator":{"name":"message-demarcator","displayName":"Message Demarcator","identifiesControllerService":false,"sensitive":false},"transactional-id-prefix":{"name":"transactional-id-prefix","displayName":"Transactional Id Prefix","identifiesControllerService":false,"sensitive":false},"ack.wait.time":{"name":"ack.wait.time","displayName":"Acknowledgment Wait Time","identifiesControllerService":false,"sensitive":false},"sasl.username":{"name":"sasl.username","displayName":"Username","identifiesControllerService":false,"sensitive":false},"use-transactions":{"name":"use-transactions","displayName":"Use Transactions","identifiesControllerService":false,"sensitive":false},"acks":{"name":"acks","displayName":"Delivery Guarantee","identifiesControllerService":false,"sensitive":false},"aws.profile.name":{"name":"aws.profile.name","displayName":"AWS Profile Name","identifiesControllerService":false,"sensitive":false},"security.protocol":{"name":"security.protocol","displayName":"Security Protocol","identifiesControllerService":false,"sensitive":false},"ssl.context.service":{"name":"ssl.context.service","displayName":"SSL Context Service","identifiesControllerService":true,"sensitive":false},"max.request.size":{"name":"max.request.size","displayName":"Max Request Size","identifiesControllerService":false,"sensitive":false},"sasl.token.auth":{"name":"sasl.token.auth","displayName":"Token Authentication","identifiesControllerService":false,"sensitive":false},"Failure Strategy":{"name":"Failure Strategy","displayName":"Failure Strategy","identifiesControllerService":false,"sensitive":false},"partitioner.class":{"name":"partitioner.class","displayName":"Partitioner class","identifiesControllerService":false,"sensitive":false},"sasl.kerberos.keytab":{"name":"sasl.kerberos.keytab","displayName":"Kerberos Keytab","identifiesControllerService":false,"sensitive":false,"resourceDefinition":{"cardinality":"SINGLE","resourceTypes":["FILE"]}},"topic":{"name":"topic","displayName":"Topic Name","identifiesControllerService":false,"sensitive":false},"sasl.password":{"name":"sasl.password","displayName":"Password","identifiesControllerService":false,"sensitive":true},"key-attribute-encoding":{"name":"key-attribute-encoding","displayName":"Key Attribute Encoding","identifiesControllerService":false,"sensitive":false}},"style":{},"schedulingPeriod":"0 sec","schedulingStrategy":"TIMER_DRIVEN","executionNode":"ALL","penaltyDuration":"30 sec","yieldDuration":"1 sec","bulletinLevel":"WARN","runDurationMillis":0,"concurrentlySchedulableTaskCount":1,"autoTerminatedRelationships":[],"scheduledState":"ENABLED","retryCount":10,"retriedRelationships":[],"backoffMechanism":"PENALIZE_FLOWFILE","maxBackoffPeriod":"10 mins","componentType":"PROCESSOR","groupIdentifier":"8f23d57e-775a-3044-a314-9d0f58900aa2"},{"identifier":"33f73d7c-5f00-3edb-891d-d39aef5bf7b1","instanceIdentifier":"8c743f5f-1d79-1028-aa15-107f57a23291","name":"EvaluateJsonPath","comments":"","position":{"x":233.93452783658591,"y":377.47522863994436},"type":"org.apache.nifi.processors.standard.EvaluateJsonPath","bundle":{"group":"org.apache.nifi","artifact":"nifi-standard-nar","version":"1.20.0"},"properties":{"Destination":"flowfile-attribute","ResourceId":"$.ResourceId","Return Type":"auto-detect","Null Value Representation":"empty string","Path Not Found Behavior":"ignore"},"propertyDescriptors":{"Destination":{"name":"Destination","displayName":"Destination","identifiesControllerService":false,"sensitive":false},"ResourceId":{"name":"ResourceId","displayName":"ResourceId","identifiesControllerService":false,"sensitive":false},"Return Type":{"name":"Return Type","displayName":"Return Type","identifiesControllerService":false,"sensitive":false},"Null Value Representation":{"name":"Null Value Representation","displayName":"Null Value Representation","identifiesControllerService":false,"sensitive":false},"Path Not Found Behavior":{"name":"Path Not Found Behavior","displayName":"Path Not Found Behavior","identifiesControllerService":false,"sensitive":false}},"style":{},"schedulingPeriod":"0 sec","schedulingStrategy":"TIMER_DRIVEN","executionNode":"ALL","penaltyDuration":"30 sec","yieldDuration":"1 sec","bulletinLevel":"WARN","runDurationMillis":0,"concurrentlySchedulableTaskCount":1,"autoTerminatedRelationships":[],"scheduledState":"ENABLED","retryCount":10,"retriedRelationships":[],"backoffMechanism":"PENALIZE_FLOWFILE","maxBackoffPeriod":"10 mins","componentType":"PROCESSOR","groupIdentifier":"8f23d57e-775a-3044-a314-9d0f58900aa2"},{"identifier":"4dada7ab-68f3-3bd4-b62c-a7c21c6c016a","instanceIdentifier":"8c743f83-1d79-1028-06d8-e633fedfb3eb","name":"JoltTransformJSON","comments":"","position":{"x":-680.0,"y":1440.0},"type":"org.apache.nifi.processors.standard.JoltTransformJSON","bundle":{"group":"org.apache.nifi","artifact":"nifi-standard-nar","version":"1.20.0"},"properties":{"jolt-spec":"[\n  {\n    \"operation\": \"remove\",\n    \"spec\": {\n      \"*\": \"\"\n    }\n  },\n  {\n    \"operation\": \"default\",\n    \"spec\": {\n\t\t\"Status\" : \"${Status}\",\n      \t\"ResourceId\" : \"${ResourceId}\",\n      \t\"Name\" : \"${Name}\",\n      \t\"AssetOwner\" : \"${AssetOwner}\",\n      \t\"Cloud\" : \"${Cloud}\",\n      \t\"CreationTime\" : \"${CreationTime}\",\n      \t\"AllAppsActive\" : \"${AllAppsActive}\",\n      \t\"Applications\" : {\n          \"Antivirus\" : \"${Antivirus}\",\n          \"DLP\" : \"${DLP}\",\n          \"Firewall\" : \"${Firewall}\",\n          \"DiscEncryption\" : \"${DiscEncryption}\"\n        }\n    }\n  }\n]\n","jolt-transform":"jolt-transform-chain","jolt-custom-class":null,"jolt-custom-modules":null,"pretty_print":"false","Transform Cache Size":"1"},"propertyDescriptors":{"jolt-spec":{"name":"jolt-spec","displayName":"Jolt Specification","identifiesControllerService":false,"sensitive":false},"jolt-transform":{"name":"jolt-transform","displayName":"Jolt Transformation DSL","identifiesControllerService":false,"sensitive":false},"jolt-custom-class":{"name":"jolt-custom-class","displayName":"Custom Transformation Class Name","identifiesControllerService":false,"sensitive":false},"jolt-custom-modules":{"name":"jolt-custom-modules","displayName":"Custom Module Directory","identifiesControllerService":false,"sensitive":false,"resourceDefinition":{"cardinality":"MULTIPLE","resourceTypes":["FILE","DIRECTORY"]}},"pretty_print":{"name":"pretty_print","displayName":"Pretty Print","identifiesControllerService":false,"sensitive":false},"Transform Cache Size":{"name":"Transform Cache Size","displayName":"Transform Cache Size","identifiesControllerService":false,"sensitive":false}},"style":{},"schedulingPeriod":"0 sec","schedulingStrategy":"TIMER_DRIVEN","executionNode":"ALL","penaltyDuration":"30 sec","yieldDuration":"1 sec","bulletinLevel":"WARN","runDurationMillis":0,"concurrentlySchedulableTaskCount":1,"autoTerminatedRelationships":[],"scheduledState":"ENABLED","retryCount":10,"retriedRelationships":[],"backoffMechanism":"PENALIZE_FLOWFILE","maxBackoffPeriod":"10 mins","componentType":"PROCESSOR","groupIdentifier":"8f23d57e-775a-3044-a314-9d0f58900aa2"},{"identifier":"71bbdb43-9619-3e81-bd8b-4c2faf182519","instanceIdentifier":"8c743f5d-1d79-1028-f658-aa1ea5972c67","name":"SplitJson","comments":"","position":{"x":241.93452783658591,"y":153.47522863994436},"type":"org.apache.nifi.processors.standard.SplitJson","bundle":{"group":"org.apache.nifi","artifact":"nifi-standard-nar","version":"1.20.0"},"properties":{"Null Value Representation":"empty string","JsonPath Expression":"$.*"},"propertyDescriptors":{"Null Value Representation":{"name":"Null Value Representation","displayName":"Null Value Representation","identifiesControllerService":false,"sensitive":false},"JsonPath Expression":{"name":"JsonPath Expression","displayName":"JsonPath Expression","identifiesControllerService":false,"sensitive":false}},"style":{},"schedulingPeriod":"0 sec","schedulingStrategy":"TIMER_DRIVEN","executionNode":"ALL","penaltyDuration":"30 sec","yieldDuration":"1 sec","bulletinLevel":"WARN","runDurationMillis":0,"concurrentlySchedulableTaskCount":1,"autoTerminatedRelationships":[],"scheduledState":"ENABLED","retryCount":10,"retriedRelationships":[],"backoffMechanism":"PENALIZE_FLOWFILE","maxBackoffPeriod":"10 mins","componentType":"PROCESSOR","groupIdentifier":"8f23d57e-775a-3044-a314-9d0f58900aa2"},{"identifier":"acba2c18-a489-3617-95e6-b08b072dd24d","instanceIdentifier":"8c743f70-1d79-1028-6da7-d16a2451b1ed","name":"EvaluateJsonPath","comments":"","position":{"x":-672.0,"y":432.0},"type":"org.apache.nifi.processors.standard.EvaluateJsonPath","bundle":{"group":"org.apache.nifi","artifact":"nifi-standard-nar","version":"1.20.0"},"properties":{"Status":"$.Status","Destination":"flowfile-attribute","ResourceId":"$.ResourceId","DiscEncryption":"$.Applications.DiscEncryption","Return Type":"auto-detect","DLP":"$.Applications.DLP","Null Value Representation":"empty string","Antivirus":"$.Applications.Antivirus","Path Not Found Behavior":"ignore","Firewall":"$.Applications.Firewall"},"propertyDescriptors":{"Status":{"name":"Status","displayName":"Status","identifiesControllerService":false,"sensitive":false},"Destination":{"name":"Destination","displayName":"Destination","identifiesControllerService":false,"sensitive":false},"ResourceId":{"name":"ResourceId","displayName":"ResourceId","identifiesControllerService":false,"sensitive":false},"DiscEncryption":{"name":"DiscEncryption","displayName":"DiscEncryption","identifiesControllerService":false,"sensitive":false},"Return Type":{"name":"Return Type","displayName":"Return Type","identifiesControllerService":false,"sensitive":false},"DLP":{"name":"DLP","displayName":"DLP","identifiesControllerService":false,"sensitive":false},"Null Value Representation":{"name":"Null Value Representation","displayName":"Null Value Representation","identifiesControllerService":false,"sensitive":false},"Antivirus":{"name":"Antivirus","displayName":"Antivirus","identifiesControllerService":false,"sensitive":false},"Path Not Found Behavior":{"name":"Path Not Found Behavior","displayName":"Path Not Found Behavior","identifiesControllerService":false,"sensitive":false},"Firewall":{"name":"Firewall","displayName":"Firewall","identifiesControllerService":false,"sensitive":false}},"style":{},"schedulingPeriod":"0 sec","schedulingStrategy":"TIMER_DRIVEN","executionNode":"ALL","penaltyDuration":"30 sec","yieldDuration":"1 sec","bulletinLevel":"WARN","runDurationMillis":0,"concurrentlySchedulableTaskCount":1,"autoTerminatedRelationships":[],"scheduledState":"ENABLED","retryCount":10,"retriedRelationships":[],"backoffMechanism":"PENALIZE_FLOWFILE","maxBackoffPeriod":"10 mins","componentType":"PROCESSOR","groupIdentifier":"8f23d57e-775a-3044-a314-9d0f58900aa2"},{"identifier":"c9547b9d-8ffc-3534-af4d-c65fc61978a6","instanceIdentifier":"8c743f95-1d79-1028-c6bf-e3d4d9970001","name":"FetchS3Object","comments":"","position":{"x":-672.0,"y":936.0},"type":"org.apache.nifi.processors.aws.s3.FetchS3Object","bundle":{"group":"org.apache.nifi","artifact":"nifi-aws-nar","version":"1.20.0"},"properties":{"Proxy Host":null,"range-length":null,"Access Key":"#{Access Key ID}","range-start":null,"proxy-configuration-service":null,"Endpoint Override URL":"http://#{IP}:9000","custom-signer-class-name":null,"requester-pays":"false","Object Key":"${ResourceId}","AWS Credentials Provider service":null,"custom-signer-module-location":null,"SSL Context Service":null,"Signer Override":"Default Signature","Bucket":"serverreporting","Version":null,"Communications Timeout":"30 secs","Region":"us-west-2","Secret Key":"#{Secret Access Key}","Credentials File":null,"proxy-user-name":null,"Proxy Host Port":null,"encryption-service":null},"propertyDescriptors":{"Proxy Host":{"name":"Proxy Host","displayName":"Proxy Host","identifiesControllerService":false,"sensitive":false},"range-length":{"name":"range-length","displayName":"Range Length","identifiesControllerService":false,"sensitive":false},"Access Key":{"name":"Access Key","displayName":"Access Key ID","identifiesControllerService":false,"sensitive":true},"range-start":{"name":"range-start","displayName":"Range Start","identifiesControllerService":false,"sensitive":false},"proxy-configuration-service":{"name":"proxy-configuration-service","displayName":"Proxy Configuration Service","identifiesControllerService":true,"sensitive":false},"Endpoint Override URL":{"name":"Endpoint Override URL","displayName":"Endpoint Override URL","identifiesControllerService":false,"sensitive":false},"custom-signer-class-name":{"name":"custom-signer-class-name","displayName":"Custom Signer Class Name","identifiesControllerService":false,"sensitive":false},"requester-pays":{"name":"requester-pays","displayName":"Requester Pays","identifiesControllerService":false,"sensitive":false},"Object Key":{"name":"Object Key","displayName":"Object Key","identifiesControllerService":false,"sensitive":false},"AWS Credentials Provider service":{"name":"AWS Credentials Provider service","displayName":"AWS Credentials Provider Service","identifiesControllerService":true,"sensitive":false},"custom-signer-module-location":{"name":"custom-signer-module-location","displayName":"Custom Signer Module Location","identifiesControllerService":false,"sensitive":false,"resourceDefinition":{"cardinality":"MULTIPLE","resourceTypes":["FILE","DIRECTORY"]}},"SSL Context Service":{"name":"SSL Context Service","displayName":"SSL Context Service","identifiesControllerService":true,"sensitive":false},"Signer Override":{"name":"Signer Override","displayName":"Signer Override","identifiesControllerService":false,"sensitive":false},"Bucket":{"name":"Bucket","displayName":"Bucket","identifiesControllerService":false,"sensitive":false},"Version":{"name":"Version","displayName":"Version","identifiesControllerService":false,"sensitive":false},"proxy-user-password":{"name":"proxy-user-password","displayName":"Proxy Password","identifiesControllerService":false,"sensitive":true},"Communications Timeout":{"name":"Communications Timeout","displayName":"Communications Timeout","identifiesControllerService":false,"sensitive":false},"Region":{"name":"Region","displayName":"Region","identifiesControllerService":false,"sensitive":false},"Secret Key":{"name":"Secret Key","displayName":"Secret Access Key","identifiesControllerService":false,"sensitive":true},"Credentials File":{"name":"Credentials File","displayName":"Credentials File","identifiesControllerService":false,"sensitive":false,"resourceDefinition":{"cardinality":"SINGLE","resourceTypes":["FILE"]}},"proxy-user-name":{"name":"proxy-user-name","displayName":"Proxy Username","identifiesControllerService":false,"sensitive":false},"Proxy Host Port":{"name":"Proxy Host Port","displayName":"Proxy Host Port","identifiesControllerService":false,"sensitive":false},"encryption-service":{"name":"encryption-service","displayName":"Encryption Service","identifiesControllerService":true,"sensitive":false}},"style":{},"schedulingPeriod":"0 sec","schedulingStrategy":"TIMER_DRIVEN","executionNode":"ALL","penaltyDuration":"30 sec","yieldDuration":"1 sec","bulletinLevel":"WARN","runDurationMillis":0,"concurrentlySchedulableTaskCount":1,"autoTerminatedRelationships":[],"scheduledState":"ENABLED","retryCount":10,"retriedRelationships":[],"backoffMechanism":"PENALIZE_FLOWFILE","maxBackoffPeriod":"10 mins","componentType":"PROCESSOR","groupIdentifier":"8f23d57e-775a-3044-a314-9d0f58900aa2"},{"identifier":"71bd771a-33ea-3785-a9fc-6b711fd9f908","instanceIdentifier":"8c743f86-1d79-1028-2334-96ca85dd5718","name":"AllAppsActive","comments":"","position":{"x":-672.0,"y":1664.0},"type":"org.apache.nifi.processors.standard.RouteOnAttribute","bundle":{"group":"org.apache.nifi","artifact":"nifi-standard-nar","version":"1.20.0"},"properties":{"Routing Strategy":"Route to Property name","AllAppsActive":"${AllAppsActive:equals(\"YES\")}"},"propertyDescriptors":{"Routing Strategy":{"name":"Routing Strategy","displayName":"Routing Strategy","identifiesControllerService":false,"sensitive":false},"AllAppsActive":{"name":"AllAppsActive","displayName":"AllAppsActive","identifiesControllerService":false,"sensitive":false}},"style":{},"schedulingPeriod":"0 sec","schedulingStrategy":"TIMER_DRIVEN","executionNode":"ALL","penaltyDuration":"30 sec","yieldDuration":"1 sec","bulletinLevel":"WARN","runDurationMillis":25,"concurrentlySchedulableTaskCount":1,"autoTerminatedRelationships":[],"scheduledState":"ENABLED","retryCount":10,"retriedRelationships":[],"backoffMechanism":"PENALIZE_FLOWFILE","maxBackoffPeriod":"10 mins","componentType":"PROCESSOR","groupIdentifier":"8f23d57e-775a-3044-a314-9d0f58900aa2"},{"identifier":"89f806b4-14f6-32e4-88da-5a727b3ed522","instanceIdentifier":"8c743f60-1d79-1028-8eaf-4dd0d1cf8c33","name":"Enrichment","comments":"","position":{"x":240.0,"y":-72.0},"type":"org.apache.nifi.processors.standard.GenerateFlowFile","bundle":{"group":"org.apache.nifi","artifact":"nifi-standard-nar","version":"1.20.0"},"properties":{"character-set":"UTF-8","File Size":"0B","mime-type":null,"generate-ff-custom-text":"[\n{\n    \"ResourceId\" : \"aaaaaaaaaaaaaaa\",\n    \"Name\" : \"VM1\",\n    \"AssetOwner\" : \"AA11BB\",\n    \"Cloud\" : \"Azure\",\n    \"CreationTime\" : \"1704671297307\"\n},\n{\n    \"ResourceId\" : \"bbbbbbbbbbbbbbb\",\n    \"Name\" : \"VM2\",\n    \"AssetOwner\" : \"AA22BB\",\n    \"Cloud\" : \"GCP\",\n    \"CreationTime\" : \"1704611128440\"\n},\n{\n    \"ResourceId\" : \"ccccccccccccccc\",\n    \"Name\" : \"VM3\",\n    \"AssetOwner\" : \"AA33BB\",\n    \"Cloud\" : \"AWS\",\n    \"CreationTime\" : \"1704101128440\"\n},\n{\n    \"ResourceId\" : \"ddddddddddddddd\",\n    \"Name\" : \"VM4\",\n    \"AssetOwner\" : \"AA44BB\",\n    \"Cloud\" : \"Azure\",\n    \"CreationTime\" : \"1704671417114\"\n}\n]","Batch Size":"1","Unique FlowFiles":"false","Data Format":"Text"},"propertyDescriptors":{"character-set":{"name":"character-set","displayName":"Character Set","identifiesControllerService":false,"sensitive":false},"File Size":{"name":"File Size","displayName":"File Size","identifiesControllerService":false,"sensitive":false},"mime-type":{"name":"mime-type","displayName":"Mime Type","identifiesControllerService":false,"sensitive":false},"generate-ff-custom-text":{"name":"generate-ff-custom-text","displayName":"Custom Text","identifiesControllerService":false,"sensitive":false},"Batch Size":{"name":"Batch Size","displayName":"Batch Size","identifiesControllerService":false,"sensitive":false},"Unique FlowFiles":{"name":"Unique FlowFiles","displayName":"Unique FlowFiles","identifiesControllerService":false,"sensitive":false},"Data Format":{"name":"Data Format","displayName":"Data Format","identifiesControllerService":false,"sensitive":false}},"style":{},"schedulingPeriod":"1 min","schedulingStrategy":"TIMER_DRIVEN","executionNode":"PRIMARY","penaltyDuration":"30 sec","yieldDuration":"1 sec","bulletinLevel":"WARN","runDurationMillis":0,"concurrentlySchedulableTaskCount":1,"autoTerminatedRelationships":[],"scheduledState":"ENABLED","retryCount":10,"retriedRelationships":[],"backoffMechanism":"PENALIZE_FLOWFILE","maxBackoffPeriod":"10 mins","componentType":"PROCESSOR","groupIdentifier":"8f23d57e-775a-3044-a314-9d0f58900aa2"},{"identifier":"eb07ac33-2416-3d56-a564-b4847711220a","instanceIdentifier":"8c743f5e-1d79-1028-4823-2ff5ba6bb3a6","name":"PutS3Object","comments":"","position":{"x":239.48444216072124,"y":608.4797817875733},"type":"org.apache.nifi.processors.aws.s3.PutS3Object","bundle":{"group":"org.apache.nifi","artifact":"nifi-aws-nar","version":"1.20.0"},"properties":{"Proxy Host":null,"FullControl User List":"${s3.permissions.full.users}","Owner":"${s3.owner}","Access Key":"#{Access Key ID}","proxy-configuration-service":null,"Cache Control":null,"s3-object-remove-tags-prefix":"false","Endpoint Override URL":"http://#{IP}:9000","Multipart Upload Max Age Threshold":"7 days","custom-signer-class-name":null,"canned-acl":"${s3.permissions.cannedacl}","custom-signer-module-location":null,"Signer Override":"Default Signature","Content Type":null,"Secret Key":"#{Secret Access Key}","Write ACL User List":"${s3.permissions.writeacl.users}","server-side-encryption":"None","Read ACL User List":"${s3.permissions.readacl.users}","encryption-service":null,"Content Disposition":null,"Storage Class":"Standard","Multipart Part Size":"5 GB","use-chunked-encoding":"true","Object Key":"${ResourceId}","AWS Credentials Provider service":null,"Multipart Threshold":"5 GB","s3-object-tags-prefix":null,"SSL Context Service":null,"Bucket":"serverreporting","Multipart Upload AgeOff Interval":"60 min","use-path-style-access":"false","Write Permission User List":"${s3.permissions.write.users}","Communications Timeout":"30 secs","Credentials File":null,"Region":"us-west-2","Read Permission User List":"${s3.permissions.read.users}","Expiration Time Rule":null,"proxy-user-name":null,"Proxy Host Port":null,"s3-temporary-directory-multipart":"${java.io.tmpdir}"},"propertyDescriptors":{"Proxy Host":{"name":"Proxy Host","displayName":"Proxy Host","identifiesControllerService":false,"sensitive":false},"FullControl User List":{"name":"FullControl User List","displayName":"FullControl User List","identifiesControllerService":false,"sensitive":false},"Owner":{"name":"Owner","displayName":"Owner","identifiesControllerService":false,"sensitive":false},"Access Key":{"name":"Access Key","displayName":"Access Key ID","identifiesControllerService":false,"sensitive":true},"proxy-configuration-service":{"name":"proxy-configuration-service","displayName":"Proxy Configuration Service","identifiesControllerService":true,"sensitive":false},"Cache Control":{"name":"Cache Control","displayName":"Cache Control","identifiesControllerService":false,"sensitive":false},"s3-object-remove-tags-prefix":{"name":"s3-object-remove-tags-prefix","displayName":"Remove Tag Prefix","identifiesControllerService":false,"sensitive":false},"Endpoint Override URL":{"name":"Endpoint Override URL","displayName":"Endpoint Override URL","identifiesControllerService":false,"sensitive":false},"Multipart Upload Max Age Threshold":{"name":"Multipart Upload Max Age Threshold","displayName":"Multipart Upload Max Age Threshold","identifiesControllerService":false,"sensitive":false},"custom-signer-class-name":{"name":"custom-signer-class-name","displayName":"Custom Signer Class Name","identifiesControllerService":false,"sensitive":false},"canned-acl":{"name":"canned-acl","displayName":"Canned ACL","identifiesControllerService":false,"sensitive":false},"custom-signer-module-location":{"name":"custom-signer-module-location","displayName":"Custom Signer Module Location","identifiesControllerService":false,"sensitive":false,"resourceDefinition":{"cardinality":"MULTIPLE","resourceTypes":["FILE","DIRECTORY"]}},"Signer Override":{"name":"Signer Override","displayName":"Signer Override","identifiesControllerService":false,"sensitive":false},"proxy-user-password":{"name":"proxy-user-password","displayName":"Proxy Password","identifiesControllerService":false,"sensitive":true},"Content Type":{"name":"Content Type","displayName":"Content Type","identifiesControllerService":false,"sensitive":false},"Secret Key":{"name":"Secret Key","displayName":"Secret Access Key","identifiesControllerService":false,"sensitive":true},"Write ACL User List":{"name":"Write ACL User List","displayName":"Write ACL User List","identifiesControllerService":false,"sensitive":false},"server-side-encryption":{"name":"server-side-encryption","displayName":"Server Side Encryption","identifiesControllerService":false,"sensitive":false},"Read ACL User List":{"name":"Read ACL User List","displayName":"Read ACL User List","identifiesControllerService":false,"sensitive":false},"encryption-service":{"name":"encryption-service","displayName":"Encryption Service","identifiesControllerService":true,"sensitive":false},"Content Disposition":{"name":"Content Disposition","displayName":"Content Disposition","identifiesControllerService":false,"sensitive":false},"Storage Class":{"name":"Storage Class","displayName":"Storage Class","identifiesControllerService":false,"sensitive":false},"Multipart Part Size":{"name":"Multipart Part Size","displayName":"Multipart Part Size","identifiesControllerService":false,"sensitive":false},"use-chunked-encoding":{"name":"use-chunked-encoding","displayName":"Use Chunked Encoding","identifiesControllerService":false,"sensitive":false},"Object Key":{"name":"Object Key","displayName":"Object Key","identifiesControllerService":false,"sensitive":false},"AWS Credentials Provider service":{"name":"AWS Credentials Provider service","displayName":"AWS Credentials Provider Service","identifiesControllerService":true,"sensitive":false},"Multipart Threshold":{"name":"Multipart Threshold","displayName":"Multipart Threshold","identifiesControllerService":false,"sensitive":false},"s3-object-tags-prefix":{"name":"s3-object-tags-prefix","displayName":"Object Tags Prefix","identifiesControllerService":false,"sensitive":false},"SSL Context Service":{"name":"SSL Context Service","displayName":"SSL Context Service","identifiesControllerService":true,"sensitive":false},"Bucket":{"name":"Bucket","displayName":"Bucket","identifiesControllerService":false,"sensitive":false},"Multipart Upload AgeOff Interval":{"name":"Multipart Upload AgeOff Interval","displayName":"Multipart Upload AgeOff Interval","identifiesControllerService":false,"sensitive":false},"use-path-style-access":{"name":"use-path-style-access","displayName":"Use Path Style Access","identifiesControllerService":false,"sensitive":false},"Write Permission User List":{"name":"Write Permission User List","displayName":"Write Permission User List","identifiesControllerService":false,"sensitive":false},"Communications Timeout":{"name":"Communications Timeout","displayName":"Communications Timeout","identifiesControllerService":false,"sensitive":false},"Credentials File":{"name":"Credentials File","displayName":"Credentials File","identifiesControllerService":false,"sensitive":false,"resourceDefinition":{"cardinality":"SINGLE","resourceTypes":["FILE"]}},"Region":{"name":"Region","displayName":"Region","identifiesControllerService":false,"sensitive":false},"Read Permission User List":{"name":"Read Permission User List","displayName":"Read Permission User List","identifiesControllerService":false,"sensitive":false},"Expiration Time Rule":{"name":"Expiration Time Rule","displayName":"Expiration Time Rule","identifiesControllerService":false,"sensitive":false},"proxy-user-name":{"name":"proxy-user-name","displayName":"Proxy Username","identifiesControllerService":false,"sensitive":false},"Proxy Host Port":{"name":"Proxy Host Port","displayName":"Proxy Host Port","identifiesControllerService":false,"sensitive":false},"s3-temporary-directory-multipart":{"name":"s3-temporary-directory-multipart","displayName":"Temporary Directory Multipart State","identifiesControllerService":false,"sensitive":false}},"style":{},"schedulingPeriod":"0 sec","schedulingStrategy":"TIMER_DRIVEN","executionNode":"ALL","penaltyDuration":"30 sec","yieldDuration":"1 sec","bulletinLevel":"WARN","runDurationMillis":0,"concurrentlySchedulableTaskCount":1,"autoTerminatedRelationships":[],"scheduledState":"ENABLED","retryCount":10,"retriedRelationships":[],"backoffMechanism":"PENALIZE_FLOWFILE","maxBackoffPeriod":"10 mins","componentType":"PROCESSOR","groupIdentifier":"8f23d57e-775a-3044-a314-9d0f58900aa2"},{"identifier":"f1d65fa3-2246-3b54-b371-d21a7c337fc3","instanceIdentifier":"8c743f7c-1d79-1028-7c84-dc4eeddba306","name":"UpdateAttribute","comments":"","position":{"x":-672.0,"y":664.0},"type":"org.apache.nifi.processors.attributes.UpdateAttribute","bundle":{"group":"org.apache.nifi","artifact":"nifi-update-attribute-nar","version":"1.20.0"},"properties":{"Delete Attributes Expression":null,"Store State":"Do not store state","canonical-value-lookup-cache-size":"100","AllAppsActive":"${Antivirus:equals(\"YES\"):and(${DLP:equals(\"YES\"):and(${Firewall:equals(\"YES\"):and(${DiscEncryption:equals(\"YES\")})})}):ifElse(\"YES\", \"NO\")}","Stateful Variables Initial Value":null},"propertyDescriptors":{"Delete Attributes Expression":{"name":"Delete Attributes Expression","displayName":"Delete Attributes Expression","identifiesControllerService":false,"sensitive":false},"Store State":{"name":"Store State","displayName":"Store State","identifiesControllerService":false,"sensitive":false},"canonical-value-lookup-cache-size":{"name":"canonical-value-lookup-cache-size","displayName":"Cache Value Lookup Cache Size","identifiesControllerService":false,"sensitive":false},"AllAppsActive":{"name":"AllAppsActive","displayName":"AllAppsActive","identifiesControllerService":false,"sensitive":false},"Stateful Variables Initial Value":{"name":"Stateful Variables Initial Value","displayName":"Stateful Variables Initial Value","identifiesControllerService":false,"sensitive":false}},"style":{},"schedulingPeriod":"0 sec","schedulingStrategy":"TIMER_DRIVEN","executionNode":"ALL","penaltyDuration":"30 sec","yieldDuration":"1 sec","bulletinLevel":"WARN","runDurationMillis":25,"concurrentlySchedulableTaskCount":1,"autoTerminatedRelationships":[],"scheduledState":"ENABLED","retryCount":10,"retriedRelationships":[],"backoffMechanism":"PENALIZE_FLOWFILE","maxBackoffPeriod":"10 mins","componentType":"PROCESSOR","groupIdentifier":"8f23d57e-775a-3044-a314-9d0f58900aa2"},{"identifier":"7a139926-3df1-340c-8647-371a75f01947","instanceIdentifier":"8c743f96-1d79-1028-3c1a-98164651fca4","name":"EvaluateJsonPath","comments":"","position":{"x":-672.0,"y":1200.0},"type":"org.apache.nifi.processors.standard.EvaluateJsonPath","bundle":{"group":"org.apache.nifi","artifact":"nifi-standard-nar","version":"1.20.0"},"properties":{"AssetOwner":"$.AssetOwner","Destination":"flowfile-attribute","Return Type":"auto-detect","Cloud":"$.Cloud","CreationTime":"$.CreationTime","Null Value Representation":"empty string","Path Not Found Behavior":"ignore","Name":"$.Name"},"propertyDescriptors":{"AssetOwner":{"name":"AssetOwner","displayName":"AssetOwner","identifiesControllerService":false,"sensitive":false},"Destination":{"name":"Destination","displayName":"Destination","identifiesControllerService":false,"sensitive":false},"Return Type":{"name":"Return Type","displayName":"Return Type","identifiesControllerService":false,"sensitive":false},"Cloud":{"name":"Cloud","displayName":"Cloud","identifiesControllerService":false,"sensitive":false},"CreationTime":{"name":"CreationTime","displayName":"CreationTime","identifiesControllerService":false,"sensitive":false},"Null Value Representation":{"name":"Null Value Representation","displayName":"Null Value Representation","identifiesControllerService":false,"sensitive":false},"Path Not Found Behavior":{"name":"Path Not Found Behavior","displayName":"Path Not Found Behavior","identifiesControllerService":false,"sensitive":false},"Name":{"name":"Name","displayName":"Name","identifiesControllerService":false,"sensitive":false}},"style":{},"schedulingPeriod":"0 sec","schedulingStrategy":"TIMER_DRIVEN","executionNode":"ALL","penaltyDuration":"30 sec","yieldDuration":"1 sec","bulletinLevel":"WARN","runDurationMillis":0,"concurrentlySchedulableTaskCount":1,"autoTerminatedRelationships":[],"scheduledState":"ENABLED","retryCount":10,"retriedRelationships":[],"backoffMechanism":"PENALIZE_FLOWFILE","maxBackoffPeriod":"10 mins","componentType":"PROCESSOR","groupIdentifier":"8f23d57e-775a-3044-a314-9d0f58900aa2"},{"identifier":"1225a342-b2a5-375e-869b-e7533003919a","instanceIdentifier":"8c743f6f-1d79-1028-eb31-88e346d2a474","name":"SplitJson","comments":"","position":{"x":-672.0,"y":160.0},"type":"org.apache.nifi.processors.standard.SplitJson","bundle":{"group":"org.apache.nifi","artifact":"nifi-standard-nar","version":"1.20.0"},"properties":{"Null Value Representation":"empty string","JsonPath Expression":"$.*"},"propertyDescriptors":{"Null Value Representation":{"name":"Null Value Representation","displayName":"Null Value Representation","identifiesControllerService":false,"sensitive":false},"JsonPath Expression":{"name":"JsonPath Expression","displayName":"JsonPath Expression","identifiesControllerService":false,"sensitive":false}},"style":{},"schedulingPeriod":"0 sec","schedulingStrategy":"TIMER_DRIVEN","executionNode":"ALL","penaltyDuration":"30 sec","yieldDuration":"1 sec","bulletinLevel":"WARN","runDurationMillis":0,"concurrentlySchedulableTaskCount":1,"autoTerminatedRelationships":[],"scheduledState":"ENABLED","retryCount":10,"retriedRelationships":[],"backoffMechanism":"PENALIZE_FLOWFILE","maxBackoffPeriod":"10 mins","componentType":"PROCESSOR","groupIdentifier":"8f23d57e-775a-3044-a314-9d0f58900aa2"}],"inputPorts":[],"outputPorts":[],"connections":[{"identifier":"f1a69d0a-b5bd-3d94-9496-07b27ce2e4e4","instanceIdentifier":"8c743f67-1d79-1028-00c8-7c0c3be343e1","name":"","source":{"id":"eb07ac33-2416-3d56-a564-b4847711220a","type":"PROCESSOR","groupId":"8f23d57e-775a-3044-a314-9d0f58900aa2","name":"PutS3Object","comments":"","instanceIdentifier":"8c743f5e-1d79-1028-4823-2ff5ba6bb3a6"},"destination":{"id":"12bfdf7d-a115-3981-8655-ff91b4d3cf76","type":"FUNNEL","groupId":"8f23d57e-775a-3044-a314-9d0f58900aa2","name":"Funnel","comments":"","instanceIdentifier":"8c743f5c-1d79-1028-5ade-5830905c9813"},"labelIndex":1,"zIndex":0,"selectedRelationships":["success"],"backPressureObjectThreshold":10000,"backPressureDataSizeThreshold":"1 GB","flowFileExpiration":"0 sec","prioritizers":[],"bends":[],"loadBalanceStrategy":"DO_NOT_LOAD_BALANCE","partitioningAttribute":"","loadBalanceCompression":"DO_NOT_COMPRESS","componentType":"CONNECTION","groupIdentifier":"8f23d57e-775a-3044-a314-9d0f58900aa2"},{"identifier":"4a3efcef-dd98-3da2-8975-914096aa1994","instanceIdentifier":"8c743f8f-1d79-1028-4fe0-6b0f25e49e02","name":"","source":{"id":"4dada7ab-68f3-3bd4-b62c-a7c21c6c016a","type":"PROCESSOR","groupId":"8f23d57e-775a-3044-a314-9d0f58900aa2","name":"JoltTransformJSON","comments":"","instanceIdentifier":"8c743f83-1d79-1028-06d8-e633fedfb3eb"},"destination":{"id":"71bd771a-33ea-3785-a9fc-6b711fd9f908","type":"PROCESSOR","groupId":"8f23d57e-775a-3044-a314-9d0f58900aa2","name":"AllAppsActive","comments":"","instanceIdentifier":"8c743f86-1d79-1028-2334-96ca85dd5718"},"labelIndex":1,"zIndex":0,"selectedRelationships":["success"],"backPressureObjectThreshold":10000,"backPressureDataSizeThreshold":"1 GB","flowFileExpiration":"0 sec","prioritizers":[],"bends":[],"loadBalanceStrategy":"DO_NOT_LOAD_BALANCE","partitioningAttribute":"","loadBalanceCompression":"DO_NOT_COMPRESS","componentType":"CONNECTION","groupIdentifier":"8f23d57e-775a-3044-a314-9d0f58900aa2"},{"identifier":"83eae6cd-65af-3a38-986c-50bae7cef2ae","instanceIdentifier":"8c743f97-1d79-1028-e72c-02d2de2d3da6","name":"","source":{"id":"c9547b9d-8ffc-3534-af4d-c65fc61978a6","type":"PROCESSOR","groupId":"8f23d57e-775a-3044-a314-9d0f58900aa2","name":"FetchS3Object","comments":"","instanceIdentifier":"8c743f95-1d79-1028-c6bf-e3d4d9970001"},"destination":{"id":"7a139926-3df1-340c-8647-371a75f01947","type":"PROCESSOR","groupId":"8f23d57e-775a-3044-a314-9d0f58900aa2","name":"EvaluateJsonPath","comments":"","instanceIdentifier":"8c743f96-1d79-1028-3c1a-98164651fca4"},"labelIndex":1,"zIndex":0,"selectedRelationships":["success"],"backPressureObjectThreshold":10000,"backPressureDataSizeThreshold":"1 GB","flowFileExpiration":"0 sec","prioritizers":[],"bends":[],"loadBalanceStrategy":"DO_NOT_LOAD_BALANCE","partitioningAttribute":"","loadBalanceCompression":"DO_NOT_COMPRESS","componentType":"CONNECTION","groupIdentifier":"8f23d57e-775a-3044-a314-9d0f58900aa2"},{"identifier":"6ab47f2b-44ae-3eb6-90c9-3ebc00bb5a50","instanceIdentifier":"8c743f75-1d79-1028-a568-88ab33d19ab7","name":"","source":{"id":"5ab48c0b-351c-3a12-9ff2-ca0b7df74f60","type":"PROCESSOR","groupId":"8f23d57e-775a-3044-a314-9d0f58900aa2","name":"MainEvent","comments":"","instanceIdentifier":"8c743f6e-1d79-1028-db19-6e50f5a0a46c"},"destination":{"id":"1225a342-b2a5-375e-869b-e7533003919a","type":"PROCESSOR","groupId":"8f23d57e-775a-3044-a314-9d0f58900aa2","name":"SplitJson","comments":"","instanceIdentifier":"8c743f6f-1d79-1028-eb31-88e346d2a474"},"labelIndex":1,"zIndex":0,"selectedRelationships":["success"],"backPressureObjectThreshold":10000,"backPressureDataSizeThreshold":"1 GB","flowFileExpiration":"0 sec","prioritizers":[],"bends":[],"loadBalanceStrategy":"DO_NOT_LOAD_BALANCE","partitioningAttribute":"","loadBalanceCompression":"DO_NOT_COMPRESS","componentType":"CONNECTION","groupIdentifier":"8f23d57e-775a-3044-a314-9d0f58900aa2"},{"identifier":"2029be1e-b4f2-3b30-baf9-a07d0b149735","instanceIdentifier":"8c743f69-1d79-1028-63b9-68e7833c7968","name":"","source":{"id":"33f73d7c-5f00-3edb-891d-d39aef5bf7b1","type":"PROCESSOR","groupId":"8f23d57e-775a-3044-a314-9d0f58900aa2","name":"EvaluateJsonPath","comments":"","instanceIdentifier":"8c743f5f-1d79-1028-aa15-107f57a23291"},"destination":{"id":"8eb644af-1e6b-37f6-b4df-844742db1cd0","type":"FUNNEL","groupId":"8f23d57e-775a-3044-a314-9d0f58900aa2","name":"Funnel","comments":"","instanceIdentifier":"8c743f5a-1d79-1028-0c49-df936e6bce0a"},"labelIndex":1,"zIndex":0,"selectedRelationships":["failure"],"backPressureObjectThreshold":10000,"backPressureDataSizeThreshold":"1 GB","flowFileExpiration":"0 sec","prioritizers":[],"bends":[{"x":793.9345278365859,"y":409.47522863994436}],"loadBalanceStrategy":"DO_NOT_LOAD_BALANCE","partitioningAttribute":"","loadBalanceCompression":"DO_NOT_COMPRESS","componentType":"CONNECTION","groupIdentifier":"8f23d57e-775a-3044-a314-9d0f58900aa2"},{"identifier":"727dbd48-f6f0-33fb-ba85-949704036b85","instanceIdentifier":"8c743f72-1d79-1028-d42f-63010bb5e2e3","name":"","source":{"id":"acba2c18-a489-3617-95e6-b08b072dd24d","type":"PROCESSOR","groupId":"8f23d57e-775a-3044-a314-9d0f58900aa2","name":"EvaluateJsonPath","comments":"","instanceIdentifier":"8c743f70-1d79-1028-6da7-d16a2451b1ed"},"destination":{"id":"32e9ab39-db07-324b-81b2-b2e0a9e7c833","type":"FUNNEL","groupId":"8f23d57e-775a-3044-a314-9d0f58900aa2","name":"Funnel","comments":"","instanceIdentifier":"8c743f6c-1d79-1028-cdd9-8e79af410069"},"labelIndex":1,"zIndex":0,"selectedRelationships":["unmatched"],"backPressureObjectThreshold":10000,"backPressureDataSizeThreshold":"1 GB","flowFileExpiration":"0 sec","prioritizers":[],"bends":[{"x":-160.49981734178573,"y":456.7470815452143}],"loadBalanceStrategy":"DO_NOT_LOAD_BALANCE","partitioningAttribute":"","loadBalanceCompression":"DO_NOT_COMPRESS","componentType":"CONNECTION","groupIdentifier":"8f23d57e-775a-3044-a314-9d0f58900aa2"},{"identifier":"2d44be42-9c7f-3bec-b2da-7846c12e400e","instanceIdentifier":"8c743f73-1d79-1028-5cca-430eac2da3b3","name":"","source":{"id":"1225a342-b2a5-375e-869b-e7533003919a","type":"PROCESSOR","groupId":"8f23d57e-775a-3044-a314-9d0f58900aa2","name":"SplitJson","comments":"","instanceIdentifier":"8c743f6f-1d79-1028-eb31-88e346d2a474"},"destination":{"id":"af2427b9-44ab-3a3b-9578-704ea9b67305","type":"FUNNEL","groupId":"8f23d57e-775a-3044-a314-9d0f58900aa2","name":"Funnel","comments":"","instanceIdentifier":"8c743f6d-1d79-1028-c9da-446fb3a90618"},"labelIndex":1,"zIndex":0,"selectedRelationships":["original"],"backPressureObjectThreshold":10000,"backPressureDataSizeThreshold":"1 GB","flowFileExpiration":"600 sec","prioritizers":[],"bends":[{"x":-192.49981734178573,"y":272.74708154521426}],"loadBalanceStrategy":"DO_NOT_LOAD_BALANCE","partitioningAttribute":"","loadBalanceCompression":"DO_NOT_COMPRESS","componentType":"CONNECTION","groupIdentifier":"8f23d57e-775a-3044-a314-9d0f58900aa2"},{"identifier":"be60443b-86d5-30b2-8801-920d160b1f04","instanceIdentifier":"8c743f8b-1d79-1028-3063-4f52775a3101","name":"","source":{"id":"735d6488-10b1-396f-aed4-2d4c6166c222","type":"PROCESSOR","groupId":"8f23d57e-775a-3044-a314-9d0f58900aa2","name":"serverReportingNotOK","comments":"","instanceIdentifier":"8c743f88-1d79-1028-0410-0f912f78ebca"},"destination":{"id":"645ecdfd-0e7f-34a9-9a5b-2545a553fb61","type":"FUNNEL","groupId":"8f23d57e-775a-3044-a314-9d0f58900aa2","name":"Funnel","comments":"","instanceIdentifier":"8c743f85-1d79-1028-7de8-e06d0390f477"},"labelIndex":1,"zIndex":0,"selectedRelationships":["success"],"backPressureObjectThreshold":10000,"backPressureDataSizeThreshold":"1 GB","flowFileExpiration":"0 sec","prioritizers":[],"bends":[],"loadBalanceStrategy":"DO_NOT_LOAD_BALANCE","partitioningAttribute":"","loadBalanceCompression":"DO_NOT_COMPRESS","componentType":"CONNECTION","groupIdentifier":"8f23d57e-775a-3044-a314-9d0f58900aa2"},{"identifier":"df417cea-146c-3bf6-a13e-25ee90453b6c","instanceIdentifier":"8c743f63-1d79-1028-72ee-1935779bdabf","name":"","source":{"id":"89f806b4-14f6-32e4-88da-5a727b3ed522","type":"PROCESSOR","groupId":"8f23d57e-775a-3044-a314-9d0f58900aa2","name":"Enrichment","comments":"","instanceIdentifier":"8c743f60-1d79-1028-8eaf-4dd0d1cf8c33"},"destination":{"id":"71bbdb43-9619-3e81-bd8b-4c2faf182519","type":"PROCESSOR","groupId":"8f23d57e-775a-3044-a314-9d0f58900aa2","name":"SplitJson","comments":"","instanceIdentifier":"8c743f5d-1d79-1028-f658-aa1ea5972c67"},"labelIndex":1,"zIndex":0,"selectedRelationships":["success"],"backPressureObjectThreshold":10000,"backPressureDataSizeThreshold":"1 GB","flowFileExpiration":"0 sec","prioritizers":[],"bends":[],"loadBalanceStrategy":"DO_NOT_LOAD_BALANCE","partitioningAttribute":"","loadBalanceCompression":"DO_NOT_COMPRESS","componentType":"CONNECTION","groupIdentifier":"8f23d57e-775a-3044-a314-9d0f58900aa2"},{"identifier":"45a5a506-a87e-3854-81c5-141814c2be1b","instanceIdentifier":"8c743f68-1d79-1028-2ed0-e619c53c2a54","name":"","source":{"id":"71bbdb43-9619-3e81-bd8b-4c2faf182519","type":"PROCESSOR","groupId":"8f23d57e-775a-3044-a314-9d0f58900aa2","name":"SplitJson","comments":"","instanceIdentifier":"8c743f5d-1d79-1028-f658-aa1ea5972c67"},"destination":{"id":"33f73d7c-5f00-3edb-891d-d39aef5bf7b1","type":"PROCESSOR","groupId":"8f23d57e-775a-3044-a314-9d0f58900aa2","name":"EvaluateJsonPath","comments":"","instanceIdentifier":"8c743f5f-1d79-1028-aa15-107f57a23291"},"labelIndex":1,"zIndex":0,"selectedRelationships":["split"],"backPressureObjectThreshold":10000,"backPressureDataSizeThreshold":"1 GB","flowFileExpiration":"0 sec","prioritizers":[],"bends":[],"loadBalanceStrategy":"DO_NOT_LOAD_BALANCE","partitioningAttribute":"","loadBalanceCompression":"DO_NOT_COMPRESS","componentType":"CONNECTION","groupIdentifier":"8f23d57e-775a-3044-a314-9d0f58900aa2"},{"identifier":"4220bd95-444e-3bdb-b512-d0d7292de9b6","instanceIdentifier":"8c743f65-1d79-1028-315d-ec3722f47ca9","name":"","source":{"id":"33f73d7c-5f00-3edb-891d-d39aef5bf7b1","type":"PROCESSOR","groupId":"8f23d57e-775a-3044-a314-9d0f58900aa2","name":"EvaluateJsonPath","comments":"","instanceIdentifier":"8c743f5f-1d79-1028-aa15-107f57a23291"},"destination":{"id":"eb07ac33-2416-3d56-a564-b4847711220a","type":"PROCESSOR","groupId":"8f23d57e-775a-3044-a314-9d0f58900aa2","name":"PutS3Object","comments":"","instanceIdentifier":"8c743f5e-1d79-1028-4823-2ff5ba6bb3a6"},"labelIndex":1,"zIndex":0,"selectedRelationships":["matched"],"backPressureObjectThreshold":10000,"backPressureDataSizeThreshold":"1 GB","flowFileExpiration":"0 sec","prioritizers":[],"bends":[],"loadBalanceStrategy":"DO_NOT_LOAD_BALANCE","partitioningAttribute":"","loadBalanceCompression":"DO_NOT_COMPRESS","componentType":"CONNECTION","groupIdentifier":"8f23d57e-775a-3044-a314-9d0f58900aa2"},{"identifier":"e29a0fca-344d-3fe3-aaae-9f4c13261e51","instanceIdentifier":"8c743f8a-1d79-1028-3302-19dafd7d0824","name":"","source":{"id":"71bd771a-33ea-3785-a9fc-6b711fd9f908","type":"PROCESSOR","groupId":"8f23d57e-775a-3044-a314-9d0f58900aa2","name":"AllAppsActive","comments":"","instanceIdentifier":"8c743f86-1d79-1028-2334-96ca85dd5718"},"destination":{"id":"735d6488-10b1-396f-aed4-2d4c6166c222","type":"PROCESSOR","groupId":"8f23d57e-775a-3044-a314-9d0f58900aa2","name":"serverReportingNotOK","comments":"","instanceIdentifier":"8c743f88-1d79-1028-0410-0f912f78ebca"},"labelIndex":1,"zIndex":0,"selectedRelationships":["unmatched"],"backPressureObjectThreshold":10000,"backPressureDataSizeThreshold":"1 GB","flowFileExpiration":"0 sec","prioritizers":[],"bends":[],"loadBalanceStrategy":"DO_NOT_LOAD_BALANCE","partitioningAttribute":"","loadBalanceCompression":"DO_NOT_COMPRESS","componentType":"CONNECTION","groupIdentifier":"8f23d57e-775a-3044-a314-9d0f58900aa2"},{"identifier":"74cb5668-6537-3a4f-b474-a954d58fde07","instanceIdentifier":"8c743f74-1d79-1028-d245-5ed7641f10b7","name":"","source":{"id":"1225a342-b2a5-375e-869b-e7533003919a","type":"PROCESSOR","groupId":"8f23d57e-775a-3044-a314-9d0f58900aa2","name":"SplitJson","comments":"","instanceIdentifier":"8c743f6f-1d79-1028-eb31-88e346d2a474"},"destination":{"id":"acba2c18-a489-3617-95e6-b08b072dd24d","type":"PROCESSOR","groupId":"8f23d57e-775a-3044-a314-9d0f58900aa2","name":"EvaluateJsonPath","comments":"","instanceIdentifier":"8c743f70-1d79-1028-6da7-d16a2451b1ed"},"labelIndex":1,"zIndex":0,"selectedRelationships":["split"],"backPressureObjectThreshold":10000,"backPressureDataSizeThreshold":"1 GB","flowFileExpiration":"0 sec","prioritizers":[],"bends":[],"loadBalanceStrategy":"DO_NOT_LOAD_BALANCE","partitioningAttribute":"","loadBalanceCompression":"DO_NOT_COMPRESS","componentType":"CONNECTION","groupIdentifier":"8f23d57e-775a-3044-a314-9d0f58900aa2"},{"identifier":"6fa36fa8-756c-3b83-a10f-14e04192fcb8","instanceIdentifier":"8c743f7d-1d79-1028-4687-0ebf684595e4","name":"","source":{"id":"f1d65fa3-2246-3b54-b371-d21a7c337fc3","type":"PROCESSOR","groupId":"8f23d57e-775a-3044-a314-9d0f58900aa2","name":"UpdateAttribute","comments":"","instanceIdentifier":"8c743f7c-1d79-1028-7c84-dc4eeddba306"},"destination":{"id":"c9547b9d-8ffc-3534-af4d-c65fc61978a6","type":"PROCESSOR","groupId":"8f23d57e-775a-3044-a314-9d0f58900aa2","name":"FetchS3Object","comments":"","instanceIdentifier":"8c743f95-1d79-1028-c6bf-e3d4d9970001"},"labelIndex":1,"zIndex":0,"selectedRelationships":["success"],"backPressureObjectThreshold":10000,"backPressureDataSizeThreshold":"1 GB","flowFileExpiration":"0 sec","prioritizers":[],"bends":[],"loadBalanceStrategy":"DO_NOT_LOAD_BALANCE","partitioningAttribute":"","loadBalanceCompression":"DO_NOT_COMPRESS","componentType":"CONNECTION","groupIdentifier":"8f23d57e-775a-3044-a314-9d0f58900aa2"},{"identifier":"c9e311f8-84f0-3725-bb7b-17607ab73b8f","instanceIdentifier":"8c743f90-1d79-1028-c9a2-fb6e20defddc","name":"","source":{"id":"4dada7ab-68f3-3bd4-b62c-a7c21c6c016a","type":"PROCESSOR","groupId":"8f23d57e-775a-3044-a314-9d0f58900aa2","name":"JoltTransformJSON","comments":"","instanceIdentifier":"8c743f83-1d79-1028-06d8-e633fedfb3eb"},"destination":{"id":"7c6be22e-f2dc-3d83-9acd-b294cf0c188f","type":"FUNNEL","groupId":"8f23d57e-775a-3044-a314-9d0f58900aa2","name":"Funnel","comments":"","instanceIdentifier":"8c743f77-1d79-1028-2b9c-4a11dcb2064a"},"labelIndex":1,"zIndex":0,"selectedRelationships":["failure"],"backPressureObjectThreshold":10000,"backPressureDataSizeThreshold":"1 GB","flowFileExpiration":"0 sec","prioritizers":[],"bends":[],"loadBalanceStrategy":"DO_NOT_LOAD_BALANCE","partitioningAttribute":"","loadBalanceCompression":"DO_NOT_COMPRESS","componentType":"CONNECTION","groupIdentifier":"8f23d57e-775a-3044-a314-9d0f58900aa2"},{"identifier":"b4df0700-8e16-3bb3-a122-093d7a4afb77","instanceIdentifier":"8c743f91-1d79-1028-5bf1-5fd8bd93c8bd","name":"","source":{"id":"71bd771a-33ea-3785-a9fc-6b711fd9f908","type":"PROCESSOR","groupId":"8f23d57e-775a-3044-a314-9d0f58900aa2","name":"AllAppsActive","comments":"","instanceIdentifier":"8c743f86-1d79-1028-2334-96ca85dd5718"},"destination":{"id":"bd5f4a21-c580-3dfc-b35a-3aa084501223","type":"PROCESSOR","groupId":"8f23d57e-775a-3044-a314-9d0f58900aa2","name":"serverReportingOK","comments":"","instanceIdentifier":"8c743f87-1d79-1028-27ed-cb6be5dc3f5e"},"labelIndex":1,"zIndex":0,"selectedRelationships":["AllAppsActive"],"backPressureObjectThreshold":10000,"backPressureDataSizeThreshold":"1 GB","flowFileExpiration":"0 sec","prioritizers":[],"bends":[],"loadBalanceStrategy":"DO_NOT_LOAD_BALANCE","partitioningAttribute":"","loadBalanceCompression":"DO_NOT_COMPRESS","componentType":"CONNECTION","groupIdentifier":"8f23d57e-775a-3044-a314-9d0f58900aa2"},{"identifier":"0637a8c7-d773-3e3e-9d50-06d9031e18ec","instanceIdentifier":"8c743f62-1d79-1028-41b8-7f3ff4a234c1","name":"","source":{"id":"71bbdb43-9619-3e81-bd8b-4c2faf182519","type":"PROCESSOR","groupId":"8f23d57e-775a-3044-a314-9d0f58900aa2","name":"SplitJson","comments":"","instanceIdentifier":"8c743f5d-1d79-1028-f658-aa1ea5972c67"},"destination":{"id":"3d5258a8-6bcd-3466-9aee-35c3a7012350","type":"FUNNEL","groupId":"8f23d57e-775a-3044-a314-9d0f58900aa2","name":"Funnel","comments":"","instanceIdentifier":"8c743f59-1d79-1028-657b-24c528c8378f"},"labelIndex":1,"zIndex":0,"selectedRelationships":["failure"],"backPressureObjectThreshold":10000,"backPressureDataSizeThreshold":"1 GB","flowFileExpiration":"0 sec","prioritizers":[],"bends":[{"x":769.9345278365859,"y":185.47522863994436}],"loadBalanceStrategy":"DO_NOT_LOAD_BALANCE","partitioningAttribute":"","loadBalanceCompression":"DO_NOT_COMPRESS","componentType":"CONNECTION","groupIdentifier":"8f23d57e-775a-3044-a314-9d0f58900aa2"},{"identifier":"9a12bc33-43b3-305f-9373-144f17a8797e","instanceIdentifier":"8c743f64-1d79-1028-48f2-f9298e1e50ac","name":"","source":{"id":"71bbdb43-9619-3e81-bd8b-4c2faf182519","type":"PROCESSOR","groupId":"8f23d57e-775a-3044-a314-9d0f58900aa2","name":"SplitJson","comments":"","instanceIdentifier":"8c743f5d-1d79-1028-f658-aa1ea5972c67"},"destination":{"id":"3d5258a8-6bcd-3466-9aee-35c3a7012350","type":"FUNNEL","groupId":"8f23d57e-775a-3044-a314-9d0f58900aa2","name":"Funnel","comments":"","instanceIdentifier":"8c743f59-1d79-1028-657b-24c528c8378f"},"labelIndex":1,"zIndex":0,"selectedRelationships":["original"],"backPressureObjectThreshold":10000,"backPressureDataSizeThreshold":"1 GB","flowFileExpiration":"0 sec","prioritizers":[],"bends":[{"x":769.9345278365859,"y":257.47522863994436}],"loadBalanceStrategy":"DO_NOT_LOAD_BALANCE","partitioningAttribute":"","loadBalanceCompression":"DO_NOT_COMPRESS","componentType":"CONNECTION","groupIdentifier":"8f23d57e-775a-3044-a314-9d0f58900aa2"},{"identifier":"9887b738-19bc-3f49-8ffe-173b02f165b9","instanceIdentifier":"8c743f61-1d79-1028-bea8-6943d7dad27b","name":"","source":{"id":"33f73d7c-5f00-3edb-891d-d39aef5bf7b1","type":"PROCESSOR","groupId":"8f23d57e-775a-3044-a314-9d0f58900aa2","name":"EvaluateJsonPath","comments":"","instanceIdentifier":"8c743f5f-1d79-1028-aa15-107f57a23291"},"destination":{"id":"8eb644af-1e6b-37f6-b4df-844742db1cd0","type":"FUNNEL","groupId":"8f23d57e-775a-3044-a314-9d0f58900aa2","name":"Funnel","comments":"","instanceIdentifier":"8c743f5a-1d79-1028-0c49-df936e6bce0a"},"labelIndex":1,"zIndex":0,"selectedRelationships":["unmatched"],"backPressureObjectThreshold":10000,"backPressureDataSizeThreshold":"1 GB","flowFileExpiration":"0 sec","prioritizers":[],"bends":[{"x":785.9345278365859,"y":481.47522863994436}],"loadBalanceStrategy":"DO_NOT_LOAD_BALANCE","partitioningAttribute":"","loadBalanceCompression":"DO_NOT_COMPRESS","componentType":"CONNECTION","groupIdentifier":"8f23d57e-775a-3044-a314-9d0f58900aa2"},{"identifier":"5b006b0e-8419-3606-bc27-f5e5839037a9","instanceIdentifier":"8c743f76-1d79-1028-18fe-af1140bdf7a2","name":"","source":{"id":"1225a342-b2a5-375e-869b-e7533003919a","type":"PROCESSOR","groupId":"8f23d57e-775a-3044-a314-9d0f58900aa2","name":"SplitJson","comments":"","instanceIdentifier":"8c743f6f-1d79-1028-eb31-88e346d2a474"},"destination":{"id":"af2427b9-44ab-3a3b-9578-704ea9b67305","type":"FUNNEL","groupId":"8f23d57e-775a-3044-a314-9d0f58900aa2","name":"Funnel","comments":"","instanceIdentifier":"8c743f6d-1d79-1028-c9da-446fb3a90618"},"labelIndex":1,"zIndex":0,"selectedRelationships":["failure"],"backPressureObjectThreshold":10000,"backPressureDataSizeThreshold":"1 GB","flowFileExpiration":"0 sec","prioritizers":[],"bends":[{"x":-168.49981734178573,"y":184.74708154521426}],"loadBalanceStrategy":"DO_NOT_LOAD_BALANCE","partitioningAttribute":"","loadBalanceCompression":"DO_NOT_COMPRESS","componentType":"CONNECTION","groupIdentifier":"8f23d57e-775a-3044-a314-9d0f58900aa2"},{"identifier":"f365faea-5074-312c-b275-ef62dbe2eb10","instanceIdentifier":"8c743f9a-1d79-1028-e2a7-08a63998671d","name":"","source":{"id":"7a139926-3df1-340c-8647-371a75f01947","type":"PROCESSOR","groupId":"8f23d57e-775a-3044-a314-9d0f58900aa2","name":"EvaluateJsonPath","comments":"","instanceIdentifier":"8c743f96-1d79-1028-3c1a-98164651fca4"},"destination":{"id":"e6c898a6-e10b-3570-9244-974ee6f73f13","type":"FUNNEL","groupId":"8f23d57e-775a-3044-a314-9d0f58900aa2","name":"Funnel","comments":"","instanceIdentifier":"8c743f93-1d79-1028-9e25-fa3f785ef970"},"labelIndex":1,"zIndex":0,"selectedRelationships":["unmatched"],"backPressureObjectThreshold":10000,"backPressureDataSizeThreshold":"1 GB","flowFileExpiration":"0 sec","prioritizers":[],"bends":[{"x":-810.3798185742719,"y":1289.4286658055466}],"loadBalanceStrategy":"DO_NOT_LOAD_BALANCE","partitioningAttribute":"","loadBalanceCompression":"DO_NOT_COMPRESS","componentType":"CONNECTION","groupIdentifier":"8f23d57e-775a-3044-a314-9d0f58900aa2"},{"identifier":"d22163bb-4c12-3ec4-873c-6198c3372c0b","instanceIdentifier":"8c743f71-1d79-1028-9ac5-38256debc902","name":"","source":{"id":"acba2c18-a489-3617-95e6-b08b072dd24d","type":"PROCESSOR","groupId":"8f23d57e-775a-3044-a314-9d0f58900aa2","name":"EvaluateJsonPath","comments":"","instanceIdentifier":"8c743f70-1d79-1028-6da7-d16a2451b1ed"},"destination":{"id":"32e9ab39-db07-324b-81b2-b2e0a9e7c833","type":"FUNNEL","groupId":"8f23d57e-775a-3044-a314-9d0f58900aa2","name":"Funnel","comments":"","instanceIdentifier":"8c743f6c-1d79-1028-cdd9-8e79af410069"},"labelIndex":1,"zIndex":0,"selectedRelationships":["failure"],"backPressureObjectThreshold":10000,"backPressureDataSizeThreshold":"1 GB","flowFileExpiration":"0 sec","prioritizers":[],"bends":[{"x":-152.49981734178573,"y":568.7470815452143}],"loadBalanceStrategy":"DO_NOT_LOAD_BALANCE","partitioningAttribute":"","loadBalanceCompression":"DO_NOT_COMPRESS","componentType":"CONNECTION","groupIdentifier":"8f23d57e-775a-3044-a314-9d0f58900aa2"},{"identifier":"2c908582-e61b-3215-b98f-a56ae9423846","instanceIdentifier":"8c743f8c-1d79-1028-5de1-53df4795d024","name":"","source":{"id":"bd5f4a21-c580-3dfc-b35a-3aa084501223","type":"PROCESSOR","groupId":"8f23d57e-775a-3044-a314-9d0f58900aa2","name":"serverReportingOK","comments":"","instanceIdentifier":"8c743f87-1d79-1028-27ed-cb6be5dc3f5e"},"destination":{"id":"645ecdfd-0e7f-34a9-9a5b-2545a553fb61","type":"FUNNEL","groupId":"8f23d57e-775a-3044-a314-9d0f58900aa2","name":"Funnel","comments":"","instanceIdentifier":"8c743f85-1d79-1028-7de8-e06d0390f477"},"labelIndex":1,"zIndex":0,"selectedRelationships":["success"],"backPressureObjectThreshold":10000,"backPressureDataSizeThreshold":"1 GB","flowFileExpiration":"0 sec","prioritizers":[],"bends":[],"loadBalanceStrategy":"DO_NOT_LOAD_BALANCE","partitioningAttribute":"","loadBalanceCompression":"DO_NOT_COMPRESS","componentType":"CONNECTION","groupIdentifier":"8f23d57e-775a-3044-a314-9d0f58900aa2"},{"identifier":"73073a35-6e80-3ecd-a40a-6c597fad8564","instanceIdentifier":"8c743f8d-1d79-1028-24a8-b78ca4d1ddab","name":"","source":{"id":"735d6488-10b1-396f-aed4-2d4c6166c222","type":"PROCESSOR","groupId":"8f23d57e-775a-3044-a314-9d0f58900aa2","name":"serverReportingNotOK","comments":"","instanceIdentifier":"8c743f88-1d79-1028-0410-0f912f78ebca"},"destination":{"id":"645ecdfd-0e7f-34a9-9a5b-2545a553fb61","type":"FUNNEL","groupId":"8f23d57e-775a-3044-a314-9d0f58900aa2","name":"Funnel","comments":"","instanceIdentifier":"8c743f85-1d79-1028-7de8-e06d0390f477"},"labelIndex":1,"zIndex":0,"selectedRelationships":["failure"],"backPressureObjectThreshold":10000,"backPressureDataSizeThreshold":"1 GB","flowFileExpiration":"0 sec","prioritizers":[],"bends":[{"x":-752.0,"y":2312.0}],"loadBalanceStrategy":"DO_NOT_LOAD_BALANCE","partitioningAttribute":"","loadBalanceCompression":"DO_NOT_COMPRESS","componentType":"CONNECTION","groupIdentifier":"8f23d57e-775a-3044-a314-9d0f58900aa2"},{"identifier":"b572fd2c-239d-32de-9955-664dd3846124","instanceIdentifier":"8c743f98-1d79-1028-f3ba-95db93e2dd59","name":"","source":{"id":"c9547b9d-8ffc-3534-af4d-c65fc61978a6","type":"PROCESSOR","groupId":"8f23d57e-775a-3044-a314-9d0f58900aa2","name":"FetchS3Object","comments":"","instanceIdentifier":"8c743f95-1d79-1028-c6bf-e3d4d9970001"},"destination":{"id":"66a85fe4-9a53-3f54-b645-b890514b5893","type":"FUNNEL","groupId":"8f23d57e-775a-3044-a314-9d0f58900aa2","name":"Funnel","comments":"","instanceIdentifier":"8c743f94-1d79-1028-8257-9c6270598fc1"},"labelIndex":1,"zIndex":0,"selectedRelationships":["failure"],"backPressureObjectThreshold":10000,"backPressureDataSizeThreshold":"1 GB","flowFileExpiration":"0 sec","prioritizers":[],"bends":[],"loadBalanceStrategy":"DO_NOT_LOAD_BALANCE","partitioningAttribute":"","loadBalanceCompression":"DO_NOT_COMPRESS","componentType":"CONNECTION","groupIdentifier":"8f23d57e-775a-3044-a314-9d0f58900aa2"},{"identifier":"ef06b098-90a3-392e-8bc7-94f13678d96b","instanceIdentifier":"8c743f78-1d79-1028-b180-61d148155d26","name":"","source":{"id":"acba2c18-a489-3617-95e6-b08b072dd24d","type":"PROCESSOR","groupId":"8f23d57e-775a-3044-a314-9d0f58900aa2","name":"EvaluateJsonPath","comments":"","instanceIdentifier":"8c743f70-1d79-1028-6da7-d16a2451b1ed"},"destination":{"id":"f1d65fa3-2246-3b54-b371-d21a7c337fc3","type":"PROCESSOR","groupId":"8f23d57e-775a-3044-a314-9d0f58900aa2","name":"UpdateAttribute","comments":"","instanceIdentifier":"8c743f7c-1d79-1028-7c84-dc4eeddba306"},"labelIndex":1,"zIndex":0,"selectedRelationships":["matched"],"backPressureObjectThreshold":10000,"backPressureDataSizeThreshold":"1 GB","flowFileExpiration":"0 sec","prioritizers":[],"bends":[],"loadBalanceStrategy":"DO_NOT_LOAD_BALANCE","partitioningAttribute":"","loadBalanceCompression":"DO_NOT_COMPRESS","componentType":"CONNECTION","groupIdentifier":"8f23d57e-775a-3044-a314-9d0f58900aa2"},{"identifier":"d20857e4-017b-31bb-a35e-214298acae42","instanceIdentifier":"8c743f66-1d79-1028-4350-1d333cba44a6","name":"","source":{"id":"eb07ac33-2416-3d56-a564-b4847711220a","type":"PROCESSOR","groupId":"8f23d57e-775a-3044-a314-9d0f58900aa2","name":"PutS3Object","comments":"","instanceIdentifier":"8c743f5e-1d79-1028-4823-2ff5ba6bb3a6"},"destination":{"id":"564ec470-eb19-3130-bb0a-9670e74b781e","type":"FUNNEL","groupId":"8f23d57e-775a-3044-a314-9d0f58900aa2","name":"Funnel","comments":"","instanceIdentifier":"8c743f5b-1d79-1028-5009-fc5660281f85"},"labelIndex":1,"zIndex":0,"selectedRelationships":["failure"],"backPressureObjectThreshold":10000,"backPressureDataSizeThreshold":"1 GB","flowFileExpiration":"0 sec","prioritizers":[],"bends":[],"loadBalanceStrategy":"DO_NOT_LOAD_BALANCE","partitioningAttribute":"","loadBalanceCompression":"DO_NOT_COMPRESS","componentType":"CONNECTION","groupIdentifier":"8f23d57e-775a-3044-a314-9d0f58900aa2"},{"identifier":"ee1ea337-7554-38a1-98f1-54c9915658cd","instanceIdentifier":"8c743f9b-1d79-1028-43e3-e1f39391827d","name":"","source":{"id":"7a139926-3df1-340c-8647-371a75f01947","type":"PROCESSOR","groupId":"8f23d57e-775a-3044-a314-9d0f58900aa2","name":"EvaluateJsonPath","comments":"","instanceIdentifier":"8c743f96-1d79-1028-3c1a-98164651fca4"},"destination":{"id":"4dada7ab-68f3-3bd4-b62c-a7c21c6c016a","type":"PROCESSOR","groupId":"8f23d57e-775a-3044-a314-9d0f58900aa2","name":"JoltTransformJSON","comments":"","instanceIdentifier":"8c743f83-1d79-1028-06d8-e633fedfb3eb"},"labelIndex":1,"zIndex":0,"selectedRelationships":["matched"],"backPressureObjectThreshold":10000,"backPressureDataSizeThreshold":"1 GB","flowFileExpiration":"0 sec","prioritizers":[],"bends":[],"loadBalanceStrategy":"DO_NOT_LOAD_BALANCE","partitioningAttribute":"","loadBalanceCompression":"DO_NOT_COMPRESS","componentType":"CONNECTION","groupIdentifier":"8f23d57e-775a-3044-a314-9d0f58900aa2"},{"identifier":"1ad7e33c-eed4-3d3c-95ca-d9fdf5500d5b","instanceIdentifier":"8c743f8e-1d79-1028-e010-4fa39a533951","name":"","source":{"id":"bd5f4a21-c580-3dfc-b35a-3aa084501223","type":"PROCESSOR","groupId":"8f23d57e-775a-3044-a314-9d0f58900aa2","name":"serverReportingOK","comments":"","instanceIdentifier":"8c743f87-1d79-1028-27ed-cb6be5dc3f5e"},"destination":{"id":"645ecdfd-0e7f-34a9-9a5b-2545a553fb61","type":"FUNNEL","groupId":"8f23d57e-775a-3044-a314-9d0f58900aa2","name":"Funnel","comments":"","instanceIdentifier":"8c743f85-1d79-1028-7de8-e06d0390f477"},"labelIndex":0,"zIndex":0,"selectedRelationships":["failure"],"backPressureObjectThreshold":10000,"backPressureDataSizeThreshold":"1 GB","flowFileExpiration":"0 sec","prioritizers":[],"bends":[{"x":-192.0,"y":2312.0}],"loadBalanceStrategy":"DO_NOT_LOAD_BALANCE","partitioningAttribute":"","loadBalanceCompression":"DO_NOT_COMPRESS","componentType":"CONNECTION","groupIdentifier":"8f23d57e-775a-3044-a314-9d0f58900aa2"},{"identifier":"f2a967fd-5fa0-346e-a968-1896368f05d6","instanceIdentifier":"8c743f99-1d79-1028-5de2-3b37423c3890","name":"","source":{"id":"7a139926-3df1-340c-8647-371a75f01947","type":"PROCESSOR","groupId":"8f23d57e-775a-3044-a314-9d0f58900aa2","name":"EvaluateJsonPath","comments":"","instanceIdentifier":"8c743f96-1d79-1028-3c1a-98164651fca4"},"destination":{"id":"e6c898a6-e10b-3570-9244-974ee6f73f13","type":"FUNNEL","groupId":"8f23d57e-775a-3044-a314-9d0f58900aa2","name":"Funnel","comments":"","instanceIdentifier":"8c743f93-1d79-1028-9e25-fa3f785ef970"},"labelIndex":1,"zIndex":0,"selectedRelationships":["failure"],"backPressureObjectThreshold":10000,"backPressureDataSizeThreshold":"1 GB","flowFileExpiration":"0 sec","prioritizers":[],"bends":[{"x":-818.3798185742719,"y":1201.4286658055466}],"loadBalanceStrategy":"DO_NOT_LOAD_BALANCE","partitioningAttribute":"","loadBalanceCompression":"DO_NOT_COMPRESS","componentType":"CONNECTION","groupIdentifier":"8f23d57e-775a-3044-a314-9d0f58900aa2"}],"labels":[{"identifier":"2ebddbd4-6fa2-33c9-9b96-4706ab29c2e5","instanceIdentifier":"8c743f6b-1d79-1028-2a42-e9b36a446199","position":{"x":-864.0,"y":-144.0},"label":"INC List","zIndex":0,"width":568.0,"height":48.0,"style":{"font-size":"24px"},"componentType":"LABEL","groupIdentifier":"8f23d57e-775a-3044-a314-9d0f58900aa2"},{"identifier":"9fdd05b4-8cf2-3eb6-b522-816adfae6f62","instanceIdentifier":"8c743f58-1d79-1028-8502-d70202c3cf63","position":{"x":25.934527836585914,"y":-142.52477136005564},"label":"Enrichment  -> S3","zIndex":0,"width":568.0,"height":48.0,"style":{"font-size":"24px"},"componentType":"LABEL","groupIdentifier":"8f23d57e-775a-3044-a314-9d0f58900aa2"}],"funnels":[{"identifier":"66a85fe4-9a53-3f54-b645-b890514b5893","instanceIdentifier":"8c743f94-1d79-1028-8257-9c6270598fc1","position":{"x":-984.0,"y":976.0},"componentType":"FUNNEL","groupIdentifier":"8f23d57e-775a-3044-a314-9d0f58900aa2"},{"identifier":"645ecdfd-0e7f-34a9-9a5b-2545a553fb61","instanceIdentifier":"8c743f85-1d79-1028-7de8-e06d0390f477","position":{"x":-496.0,"y":2288.0},"componentType":"FUNNEL","groupIdentifier":"8f23d57e-775a-3044-a314-9d0f58900aa2"},{"identifier":"32e9ab39-db07-324b-81b2-b2e0a9e7c833","instanceIdentifier":"8c743f6c-1d79-1028-cdd9-8e79af410069","position":{"x":8.0,"y":480.0},"componentType":"FUNNEL","groupIdentifier":"8f23d57e-775a-3044-a314-9d0f58900aa2"},{"identifier":"564ec470-eb19-3130-bb0a-9670e74b781e","instanceIdentifier":"8c743f5b-1d79-1028-5009-fc5660281f85","position":{"x":937.9345278365859,"y":641.4752286399444},"componentType":"FUNNEL","groupIdentifier":"8f23d57e-775a-3044-a314-9d0f58900aa2"},{"identifier":"8eb644af-1e6b-37f6-b4df-844742db1cd0","instanceIdentifier":"8c743f5a-1d79-1028-0c49-df936e6bce0a","position":{"x":982.0064841600392,"y":443.15714231666016},"componentType":"FUNNEL","groupIdentifier":"8f23d57e-775a-3044-a314-9d0f58900aa2"},{"identifier":"e6c898a6-e10b-3570-9244-974ee6f73f13","instanceIdentifier":"8c743f93-1d79-1028-9e25-fa3f785ef970","position":{"x":-976.0,"y":1224.0},"componentType":"FUNNEL","groupIdentifier":"8f23d57e-775a-3044-a314-9d0f58900aa2"},{"identifier":"12bfdf7d-a115-3981-8655-ff91b4d3cf76","instanceIdentifier":"8c743f5c-1d79-1028-5ade-5830905c9813","position":{"x":401.9345278365859,"y":865.4752286399444},"componentType":"FUNNEL","groupIdentifier":"8f23d57e-775a-3044-a314-9d0f58900aa2"},{"identifier":"3d5258a8-6bcd-3466-9aee-35c3a7012350","instanceIdentifier":"8c743f59-1d79-1028-657b-24c528c8378f","position":{"x":953.9345278365859,"y":201.47522863994436},"componentType":"FUNNEL","groupIdentifier":"8f23d57e-775a-3044-a314-9d0f58900aa2"},{"identifier":"af2427b9-44ab-3a3b-9578-704ea9b67305","instanceIdentifier":"8c743f6d-1d79-1028-c9da-446fb3a90618","position":{"x":-8.0,"y":200.0},"componentType":"FUNNEL","groupIdentifier":"8f23d57e-775a-3044-a314-9d0f58900aa2"},{"identifier":"7c6be22e-f2dc-3d83-9acd-b294cf0c188f","instanceIdentifier":"8c743f77-1d79-1028-2b9c-4a11dcb2064a","position":{"x":-992.0,"y":1464.0},"componentType":"FUNNEL","groupIdentifier":"8f23d57e-775a-3044-a314-9d0f58900aa2"}],"controllerServices":[],"variables":{},"parameterContextName":"MiKo_config","defaultFlowFileExpiration":"0 sec","defaultBackPressureObjectThreshold":10000,"defaultBackPressureDataSizeThreshold":"1 GB","componentType":"PROCESS_GROUP","flowFileConcurrency":"UNBOUNDED","flowFileOutboundPolicy":"STREAM_WHEN_AVAILABLE"},"externalControllerServices":{},"parameterContexts":{"MiKo_config":{"name":"MiKo_config","parameters":[{"name":"IP","description":"","sensitive":false,"provided":false,"value":"192.168.1.183"},{"name":"Access Key ID","description":"","sensitive":true,"provided":false},{"name":"Secret Access Key","description":"","sensitive":true,"provided":false}],"inheritedParameterContexts":[],"componentType":"PARAMETER_CONTEXT"}},"flowEncodingVersion":"1.0","parameterProviders":{},"latest":false}